Workbook

Sheet PLAN DE CUENTAS NUEVO
A1: Codigo | B1: Nombre de cuenta | C1: Imput | D1: Resultado? | E1: Tipo Sub Cta | F1: Moneda | H1: Nivel
A2: 1 | B2: ACTIVO | H2: 1
A3: 1.01 | B3: DISPONIBILIDADES | H3: 2
A4: 1.01.01 | B4: CAJAS | H4: 3
A5: 1.01.01.001 | B5: Caja | C5: 1 | D5: N | H5: 4
A6: 1.01.01.002 | B6: Caja M. Extr. U$S | C6: 2 | D6: N | F6: 2 | H6: 4
A7: 1.01.01.003 | B7: Fondo Fijo | C7: 3 | D7: N | H7: 4
A8: 1.01.01.004 | B8: Caja Central | C8: 152 | D8: N | H8: 4
A9: 1.01.01.005 | B9: Caja de seg.efect.-Bco.Rio Maipú | C9: 1974 | D9: N | H9: 4
A10: 1.01.01.006 | B10: Caja Seg-U$S-Nro 48-Bco Santander-WCL | C10: 2124 | D10: N | F10: 2 | H10: 4
A11: 1.01.01.007 | B11: Diferencia de Caja | C11: 1736 | D11: N | H11: 4
A12: 1.01.01.008 | B12: Diferencia Moneda Extranjera | C12: 1740 | D12: N | F12: 2 | H12: 4
A13: 1.01.01.009 | B13: Caja Compensación | C13: 3600 | D13: N | H13: 4
A14: 1.01.01.010 | B14: Caja Fiduciario Fid.San Pablo Este | C14: 3844 | D14: N | H14: 4
A15: 1.01.01.011 | B15: Caja Administración | C15: 3870 | D15: N | H15: 4
A16: 1.01.01.012 | B16: Caja Seg U$S-Nro 4-Bco Francés-Torres SP SRL | C16: 3874 | D16: N | F16: 2 | H16: 4
A17: 1.01.01.013 | B17: Caja M. Extr. Euros | C17: 2122 | D17: N | F17: 3 | H17: 4
A18: 1.01.02 | B18: BANCOS | H18: 3
A19: 1.01.02.001 | B19: Bancos Cta Cte | C19: 4 | D19: N | E19: 3 | H19: 4
A20: 1.01.02.002 | B20: Bancos Cajas de Ahorro | C20: 5 | D20: N | E20: 3 | H20: 4
A21: 1.01.02.003 | B21: Banco cta cte U$S | C21: 3607 | D21: N | E21: 3 | F21: 2 | H21: 4
A22: 1.02 | B22: INVERSIONES | H22: 2
A23: 1.02.01 | B23: INVERSIONES TEMPORARIAS | H23: 3
A24: 1.02.01.001 | B24: Valores Mobiliarios | C24: 6 | D24: N | H24: 4
A25: 1.02.01.002 | B25: Títulos Públicos | C25: 7 | D25: N | H25: 4
A26: 1.02.01.003 | B26: Fondo común de inversión | C26: 1977 | D26: N | E26: 3 | H26: 4
A27: 1.02.01.004 | B27: Plazos Fijos | C27: 8 | D27: N | E27: 3 | H27: 4
A28: 1.02.01.005 | B28: Intereses Plazo Fijo No Devengados | C28: 9 | D28: N | H28: 4
A29: 1.02.01.006 | B29: Plazo fijo en dólares | C29: 1973 | D29: N | E29: 3 | F29: 2 | H29: 4
A30: 1.02.02 | B30: INVERSIONES PERMANENTES | H30: 3
A31: 1.02.02.001 | B31: Inversiones en otras empresas | C31: 1905 | D31: N | H31: 4
A32: 1.02.02.002 | B32: Inversiones en Inmuebles | C32: 56 | D32: N | H32: 4
A33: 1.02.02.003 | B33: Am.Acum. Inm.p/ inversión | C33: 2097 | D33: N | H33: 4
A34: 1.02.02.004 | B34: Aportes Mejora Torres SP--MEJORA | C34: 3877 | D34: N | E34: 4 | H34: 4
A35: 1.02.02.005 | B35: Inversión de socios - Torres SP SRL | C35: 3878 | D35: N | H35: 4
A36: 1.02.02.006 | B36: Aportes DOLARES (M) Torres SP | C36: 3882 | D36: N | E36: 4 | H36: 4
A37: 1.02.02.007 | B37: Inversion General Paz 253 | C37: 3841 | D37: N | H37: 4
A38: 1.02.02.008 | B38: Inversión en Torres SP SRL | C38: 3875 | D38: N | H38: 4
A39: 1.02.02.009 | B39: Socio por cuenta prestamo Torres SP SRL | C39: 3876 | D39: N | E39: 4 | H39: 4
A40: 1.02.03 | B40: OTRAS INVERSIONES | H40: 3
A41: 1.02.03.001 | B41: Inversiones varias | C41: 3820 | D41: N | H41: 4
A42: 1.03 | B42: CREDITOS POR VENTAS | H42: 2
A43: 1.03.01 | B43: CREDITOS POR VENTAS | H43: 3
A44: 1.03.01.001 | B44: Fiduciantes | C44: 12 | D44: N | E44: 1 | H44: 4
A45: 1.03.01.002 | B45: Contratos de Locación a Cobrar | C45: 13 | D45: N | E45: 1 | H45: 4
A46: 1.03.01.003 | B46: Documentos a Cobrar | C46: 14 | D46: N | E46: 1 | H46: 4
A47: 1.03.01.004 | B47: Cheques de Terceros a Cobrar | C47: 15 | D47: N | E47: 1 | H47: 4
A48: 1.03.01.005 | B48: Alquileres a Cobrar | C48: 141 | D48: N | E48: 1 | H48: 4
A49: 1.03.01.006 | B49: Expensas a Cobrar | C49: 142 | D49: N | E49: 1 | H49: 4
A50: 1.03.01.007 | B50: Depósitos en Garantía a Cobrar | C50: 143 | D50: N | E50: 1 | H50: 4
A51: 1.03.01.008 | B51: Deudores por Ventas de inmuebles | C51: 347 | D51: N | E51: 1 | H51: 4
A52: 1.03.01.009 | B52: Operación Locación Inm. 3 | C52: 1392 | D52: N | E52: 1 | H52: 4
A53: 1.03.01.010 | B53: Comisiones a Cobrar | C53: 1347 | D53: N | E53: 1 | H53: 4
A54: 1.03.01.011 | B54: Cheques de 3 en Custodia | C54: 341 | D54: N | E54: 1 | H54: 4
A55: 1.03.01.012 | B55: Intereses a Cobrar | C55: 1389 | D55: N | E55: 1 | H55: 4
... A59: 1.03.01.016 | B59: Alquileres No Devengados | C59: 144 | D59: N | E59: 1 | H59: 4
A60: 1.03.01.017 | B60: Cuentas a cobrar en moneda extranjera | C60: 1972 | D60: N | E60: 1 | F60: 2 | H60: 4
A61: 1.03.01.018 | B61: Deudores por Ventas LOTEOS GCI | C61: 3866 | D61: N | E61: 1 | H61: 4
A62: 1.03.01.019 | B62: Deudores por Ventas LOTEOS AW | C62: 3867 | D62: N | E62: 1 | H62: 4
A63: 1.03.01.020 | B63: Deudores por Ventas LOTEOS EL | C63: 3868 | D63: N | E63: 1 | H63: 4
A64: 1.03.01.021 | B64: Deudores por Ventas LOTEOS OTROS | C64: 1822 | D64: N | E64: 1 | H64: 4
A65: 1.03.01.022 | B65: Otros Créditos a Cobrar | C65: 3851 | D65: N | H65: 4
A66: 1.03.01.023 | B66: Interes por financ. no devengado | C66: 2764 | D66: N | H66: 4
A67: 1.03.01.024 | B67: Deudores en Gestión | C67: 16 | D67: N | E67: 1 | H67: 4
A68: 1.03.01.025 | B68: Cheques Rechazados | C68: 17 | D68: N | E68: 1 | H68: 4
A69: 1.03.01.026 | B69: Serv.contratados a cobrar | C69: 1980 | D69: N | E69: 1 | H69: 4
A70: 1.03.02 | B70: PREVISION POR INCOBRABILIDADES | H70: 3
A71: 1.03.02.001 | B71: Previsión prar Créditos Incobrables | C71: 18 | D71: N | H71: 4
A72: 1.04 | B72: OTROS CREDITOS | H72: 2
A73: 1.04.01 | B73: CREDITOS FISCALES Y PREVISIONALES | H73: 3
A74: 1.04.01.001 | B74: Imp.Ganancias - Anticipos | C74: 19 | D74: N | H74: 4
A75: 1.04.01.002 | B75: Imp. a las Ganancias - Retenciones | C75: 20 | D75: N | H75: 4
A76: 1.04.01.003 | B76: Imp.a las Ganancias - Saldo a Favor | C76: 21 | D76: N | H76: 4
A77: 1.04.01.004 | B77: IVA Retenciones | C77: 22 | D77: N | H77: 4
A78: 1.04.01.005 | B78: IVA Percepciones | C78: 23 | D78: N | H78: 4
A79: 1.04.01.006 | B79: IVA Crédito Fiscal 21 % | C79: 24 | D79: N | H79: 4
A80: 1.04.01.007 | B80: IVA Crédito Fiscal 10 5 % | C80: 25 | D80: N | H80: 4
A81: 1.04.01.008 | B81: IVA Crédito Fiscal 27 % | C81: 26 | D81: N | H81: 4
A82: 1.04.01.009 | B82: IVA Saldo a Favor | C82: 27 | D82: N | H82: 4
A83: 1.04.01.010 | B83: IVA Anticipos s/ ventas | C83: 28 | D83: N | H83: 4
A84: 1.04.01.011 | B84: Ingresos Brutos Retenciones | C84: 29 | D84: N | H84: 4
A85: 1.04.01.012 | B85: Ingresos Brutos Percepciones | C85: 30 | D85: N | H85: 4
... A95: 1.04.01.022 | B95: TEM A FAVOR | C95: 3808 | D95: N | H95: 4
A96: 1.04.02 | B96: CREDITOS DIVERSOS | H96: 3
A97: 1.04.02.001 | B97: Anticipo al Personal | C97: 74 | D97: N | E97: 4 | H97: 4
A98: 1.04.02.002 | B98: Depósitos en Garantia | C98: 76 | D98: N | H98: 4
A99: 1.04.02.003 | B99: Gastos Pagados por Adelantado | C99: 77 | D99: N | H99: 4
A100: 1.04.02.004 | B100: Gastos a Recuperar-Clientes | C100: 78 | D100: N | E100: 1 | H100: 4
A101: 1.04.02.005 | B101: Fondos a Rendir | C101: 80 | D101: N | E101: 4 | H101: 4
A102: 1.04.02.006 | B102: Fondo de Reparo | C102: 81 | D102: N | E102: 1 | H102: 4
A103: 1.04.02.007 | B103: Costo vta.inm.diferido | C103: 2329 | D103: N | H103: 4
A104: 1.04.02.008 | B104: Certificado de EDET | C104: 2622 | D104: N | H104: 4
A105: 1.04.02.009 | B105: Embargos Judiciales | C105: 3494 | D105: N | H105: 4
A106: 1.04.02.010 | B106: Fondo a rendir en U$S | C106: 3883 | D106: N | E106: 4 | F106: 2 | H106: 4
A107: 1.04.03 | B107: CREDITOS CON SOCIOS Y PROPIETARIOS | H107: 3
A108: 1.04.03.001 | B108: Prestamos Socios | C108: 147 | D108: N | E108: 4 | H108: 4
A109: 1.04.03.002 | B109: Cuentas Particulares Socios | C109: 148 | D109: N | E109: 4 | H109: 4
A110: 1.04.03.003 | B110: P.I.F. | C110: 149 | D110: N | E110: 4 | H110: 4
A111: 1.04.03.004 | B111: Prestamos a y de Terceros | C111: 996 | D111: N | E111: 1 | H111: 4
A112: 1.04.03.005 | B112: Gastos a recuperar-Socios o Empl. | C112: 1362 | D112: N | E112: 4 | H112: 4
...

Sheet PLAN DE CUENTAS VIEJO
A1: PLAN DE CUENTAS VIEJO | H1: ANALISIS LUCIA | O1: CUENTA PLAN DE CUENTAS NUEVO
A2: Codigo | B2: Nombre de cuenta | C2: Imput | D2: Resultado? | E2: Tipo Sub Cta | F2: Moneda | H2: SALDO?? | I2: Mov 2023? | J2: Observacion | K2: Nivel | L2: TIPO | M2: Caracteres | O2: Codigo OK | P2: Nombre de cuenta OK | Q2: Imput OK | R2: Resultado OK | S2: Tipo Sub Cta OK | T2: Moneda OK | V2: Nivel
A3: 1 | B3: ACTIVO | D3: N | I3: =+IFERROR(VLOOKUP(C3,'Mov 2023 hasta ahora '!$C$2:$D$314,2,FALSE),"NO") -> NO | J3: ok | K3: 1 | L3: PATRIMONIAL | M3: 1
A4: 1.01 | B4: CASA CENTRAL | D4: N | I4: =+IFERROR(VLOOKUP(C4,'Mov 2023 hasta ahora '!$C$2:$D$314,2,FALSE),"NO") -> NO | J4: Eliminar | K4: 2 | L4: PATRIMONIAL | M4: 4
A5: 1.01.01 | B5: DISPONIBILIDADES | D5: N | I5: =+IFERROR(VLOOKUP(C5,'Mov 2023 hasta ahora '!$C$2:$D$314,2,FALSE),"NO") -> NO | J5: ok | K5: 3 | L5: PATRIMONIAL | M5: 10
A6: 1.01.01.01 | B6: CAJAS | D6: N | I6: =+IFERROR(VLOOKUP(C6,'Mov 2023 hasta ahora '!$C$2:$D$314,2,FALSE),"NO") -> NO | J6: ok | K6: 4 | L6: PATRIMONIAL | M6: 14
A7: 1.01.01.01.01 | B7: Caja | C7: 1 | D7: N | I7: =+IFERROR(VLOOKUP(C7,'Mov 2023 hasta ahora '!$C$2:$D$314,2,FALSE),"NO") -> 13968 | J7: ok | K7: 5 | L7: PATRIMONIAL | M7: 18 | O7: 1.01.01.001 | P7: Caja | Q7: 1 | R7: N
A8: 1.01.01.01.02 | B8: Caja M. Extr. U$S | C8: 2 | D8: N | F8: 2 | I8: =+IFERROR(VLOOKUP(C8,'Mov 2023 hasta ahora '!$C$2:$D$314,2,FALSE),"NO") -> 849 | J8: ok | K8: 5 | L8: PATRIMONIAL | M8: 18 | O8: 1.01.01.002 | P8: Caja M. Extr. U$S | Q8: 2 | R8: N | T8: =+F8 -> 2
A9: 1.01.01.01.03 | B9: Fondo Fijo | C9: 3 | D9: N | I9: =+IFERROR(VLOOKUP(C9,'Mov 2023 hasta ahora '!$C$2:$D$314,2,FALSE),"NO") -> 668 | J9: ok | K9: 5 | L9: PATRIMONIAL | M9: 18 | O9: 1.01.01.003 | P9: Fondo Fijo | Q9: 3 | R9: N
A10: 1.01.01.01.04 | B10: Caja Mg | C10: 146 | D10: N | E10: 3 | H10: NO | I10: =+IFERROR(VLOOKUP(C10,'Mov 2023 hasta ahora '!$C$2:$D$314,2,FALSE),"NO") -> NO | J10: Eliminar | K10: 5 | L10: PATRIMONIAL | M10: 18 | O10: 1.02.01.004 | P10: Plazos Fijos | Q10: 8
A11: 1.01.01.01.05 | B11: Caja Central | C11: 152 | D11: N | I11: =+IFERROR(VLOOKUP(C11,'Mov 2023 hasta ahora '!$C$2:$D$314,2,FALSE),"NO") -> 1087 | J11: ok | K11: 5 | L11: PATRIMONIAL | M11: 18 | O11: 1.01.01.004 | P11: Caja Central | Q11: 152 | R11: N
A12: 1.01.01.01.06 | B12: Mon Extranjera Maguitur | C12: 338 | D12: N | F12: 2 | H12: NO | I12: =+IFERROR(VLOOKUP(C12,'Mov 2023 hasta ahora '!$C$2:$D$314,2,FALSE),"NO") -> NO | J12: Eliminar | K12: 5 | L12: PATRIMONIAL | M12: 18 | O12: 1.01.01.002 | P12: Caja M. Extr. U$S | Q12: 2 | T12: 2
A13: 1.01.01.01.07 | B13: Caja de Seg Efec-Citibank | C13: 339 | D13: N | H13: NO | I13: =+IFERROR(VLOOKUP(C13,'Mov 2023 hasta ahora '!$C$2:$D$314,2,FALSE),"NO") -> NO | J13: Eliminar | K13: 5 | L13: PATRIMONIAL | M13: 18 | O13: 1.01.01.007 | P13: Diferencia de Caja | Q13: 1736
A14: 1.01.01.01.08 | B14: Caja de Seg M Extr.-U$S-Citibank | C14: 340 | D14: N | F14: 2 | H14: NO | I14: =+IFERROR(VLOOKUP(C14,'Mov 2023 hasta ahora '!$C$2:$D$314,2,FALSE),"NO") -> NO | J14: Eliminar | K14: 5 | L14: PATRIMONIAL | M14: 18 | O14: 1.01.01.002 | P14: Caja M. Extr. U$S | Q14: 2 | T14: 2
A15: 1.01.01.01.09 | B15: Caja Maguitur (no Usar Todavia) | C15: 1741 | D15: N | E15: 3 | H15: NO | I15: =+IFERROR(VLOOKUP(C15,'Mov 2023 hasta ahora '!$C$2:$D$314,2,FALSE),"NO") -> NO | J15: Eliminar | K15: 5 | L15: PATRIMONIAL | M15: 18 | O15: 1.02.01.004 | P15: Plazos Fijos | Q15: 8
A16: 1.01.01.01.10 | B16: Caja de seg.efect.-Bco.Rio MaipÃ¹ | C16: 1974 | D16: N | I16: =+IFERROR(VLOOKUP(C16,'Mov 2023 hasta ahora '!$C$2:$D$314,2,FALSE),"NO") -> 4 | J16: ok | K16: 5 | L16: PATRIMONIAL | M16: 18 | O16: 1.01.01.005 | P16: Caja de seg.efect.-Bco.Rio Maipú | Q16: 1974 | R16: N
A17: 1.01.01.01.11 | B17: Caja seguridad efectivo-Bco.Rio-Tribunales | C17: 1975 | D17: N | H17: NO | I17: =+IFERROR(VLOOKUP(C17,'Mov 2023 hasta ahora '!$C$2:$D$314,2,FALSE),"NO") -> NO | J17: Eliminar | K17: 5 | L17: PATRIMONIAL | M17: 18 | O17: 1.01.01.007 | P17: Diferencia de Caja | Q17: 1736
A18: 1.01.01.01.12 | B18: Caja M. Extranj.- Euros | C18: 2122 | D18: N | F18: 3 | H18: NO | I18: =+IFERROR(VLOOKUP(C18,'Mov 2023 hasta ahora '!$C$2:$D$314,2,FALSE),"NO") -> NO | J18: Eliminar | K18: 5 | L18: PATRIMONIAL | M18: 18 | O18: 1.01.01.013 | P18: Caja M. Extr. Euros | Q18: 2122
A19: 1.01.01.01.13 | B19: Caja Seg M.Extr.-U$S-Bco.Rio Tribunales | C19: 2123 | D19: N | F19: 2 | H19: NO | I19: =+IFERROR(VLOOKUP(C19,'Mov 2023 hasta ahora '!$C$2:$D$314,2,FALSE),"NO") -> NO | J19: Eliminar | K19: 5 | L19: PATRIMONIAL | M19: 18 | O19: 1.01.01.002 | P19: Caja M. Extr. U$S | Q19: 2 | T19: 2
A20: 1.01.01.01.14 | B20: Caja Seg-U$S-Nro 48-Bco Santander-WCL | C20: 2124 | D20: N | F20: 2 | I20: =+IFERROR(VLOOKUP(C20,'Mov 2023 hasta ahora '!$C$2:$D$314,2,FALSE),"NO") -> 175 | J20: ok | K20: 5 | L20: PATRIMONIAL | M20: 18 | O20: 1.01.01.006 | P20: Caja Seg-U$S-Nro 48-Bco Santander-WCL | Q20: 2124 | R20: N | T20: =+F20 -> 2
A21: 1.01.01.01.15 | B21: Caja M.Extr-Euros-Citibank | C21: 2125 | D21: N | F21: 3 | H21: NO | I21: =+IFERROR(VLOOKUP(C21,'Mov 2023 hasta ahora '!$C$2:$D$314,2,FALSE),"NO") -> NO | J21: Eliminar | K21: 5 | L21: PATRIMONIAL | M21: 18 | O21: 1.01.01.013 | P21: Caja M. Extr. Euros | Q21: 2122
A22: 1.01.01.01.16 | B22: Caja Seg M.Extr.-Euros-Tribunales-Bco.Rio | C22: 2126 | D22: N | F22: 3 | H22: NO | I22: =+IFERROR(VLOOKUP(C22,'Mov 2023 hasta ahora '!$C$2:$D$314,2,FALSE),"NO") -> NO | J22: Eliminar | K22: 5 | L22: PATRIMONIAL | M22: 18 | O22: 1.01.01.013 | P22: Caja M. Extr. Euros | Q22: 2122
A23: 1.01.01.01.17 | B23: Caja Seg.M.Extr.- Euros-Maipu-Bco.Rio | C23: 2127 | D23: N | F23: 3 | H23: NO | I23: =+IFERROR(VLOOKUP(C23,'Mov 2023 hasta ahora '!$C$2:$D$314,2,FALSE),"NO") -> NO | J23: Eliminar | K23: 5 | L23: PATRIMONIAL | M23: 18 | O23: 1.01.01.013 | P23: Caja M. Extr. Euros | Q23: 2122
A24: 1.01.01.01.18 | B24: Caja de seg.Efect.-Anta La Rinconada | C24: 2987 | D24: N | H24: NO | I24: =+IFERROR(VLOOKUP(C24,'Mov 2023 hasta ahora '!$C$2:$D$314,2,FALSE),"NO") -> NO | J24: Eliminar | K24: 5 | L24: PATRIMONIAL | M24: 18 | O24: 1.01.01.007 | P24: Diferencia de Caja | Q24: 1736
A25: 1.01.01.01.19 | B25: Caja de Segur.-Dolares-Anta La Rinconada | C25: 2988 | D25: N | H25: NO | I25: =+IFERROR(VLOOKUP(C25,'Mov 2023 hasta ahora '!$C$2:$D$314,2,FALSE),"NO") -> NO | J25: Eliminar | K25: 5 | L25: PATRIMONIAL | M25: 18 | O25: 1.01.01.007 | P25: Diferencia de Caja | Q25: 1736
A26: 1.01.01.01.20 | B26: Diferencia de Caja | C26: 1736 | D26: N | I26: =+IFERROR(VLOOKUP(C26,'Mov 2023 hasta ahora '!$C$2:$D$314,2,FALSE),"NO") -> 83 | J26: ok | K26: 5 | L26: PATRIMONIAL | M26: 18 | O26: 1.01.01.007 | P26: Diferencia de Caja | Q26: 1736 | R26: N
A27: 1.01.01.01.21 | B27: Diferencia Caja Maguitur | C27: 1739 | D27: N | H27: NO | I27: =+IFERROR(VLOOKUP(C27,'Mov 2023 hasta ahora '!$C$2:$D$314,2,FALSE),"NO") -> NO | J27: Eliminar | K27: 5 | L27: PATRIMONIAL | M27: 18 | O27: 1.01.01.007 | P27: Diferencia de Caja | Q27: 1736
A28: 1.01.01.01.22 | B28: Diferencia Moneda Extranjera | C28: 1740 | D28: N | F28: 2 | I28: =+IFERROR(VLOOKUP(C28,'Mov 2023 hasta ahora '!$C$2:$D$314,2,FALSE),"NO") -> 13 | J28: ok | K28: 5 | L28: PATRIMONIAL | M28: 18 | O28: 1.01.01.008 | P28: Diferencia Moneda Extranjera | Q28: 1740 | R28: N | T28: =+F28 -> 2
A29: 1.01.01.01.23 | B29: Caja de seg.MaipÃ Efect. PCIW-3/4 | C29: 2694 | D29: N | H29: NO | I29: =+IFERROR(VLOOKUP(C29,'Mov 2023 hasta ahora '!$C$2:$D$314,2,FALSE),"NO") -> NO | J29: Eliminar | K29: 5 | L29: PATRIMONIAL | M29: 18 | O29: 1.01.01.007 | P29: Diferencia de Caja | Q29: 1736
A30: 1.01.01.01.24 | B30: Caja seg. Maipú U$S PCIW 3/4 | C30: 2695 | D30: N | F30: 2 | H30: NO | I30: =+IFERROR(VLOOKUP(C30,'Mov 2023 hasta ahora '!$C$2:$D$314,2,FALSE),"NO") -> NO | J30: Eliminar | K30: 5 | L30: PATRIMONIAL | M30: 18 | O30: 1.01.01.002 | P30: Caja M. Extr. U$S | Q30: 2 | T30: 2
A31: 1.01.01.01.25 | B31: Caja seg. Maipú Euros PCIW 3/4 | C31: 2696 | D31: N | F31: 3 | H31: NO | I31: =+IFERROR(VLOOKUP(C31,'Mov 2023 hasta ahora '!$C$2:$D$314,2,FALSE),"NO") -> NO | J31: Eliminar | K31: 5 | L31: PATRIMONIAL | M31: 18 | O31: 1.01.01.013 | P31: Caja M. Extr. Euros | Q31: 2122
A32: 1.01.01.01.26 | B32: Caja DroguerÃ­a | C32: 3435 | D32: N | H32: NO | I32: =+IFERROR(VLOOKUP(C32,'Mov 2023 hasta ahora '!$C$2:$D$314,2,FALSE),"NO") -> NO | J32: Eliminar | K32: 5 | L32: PATRIMONIAL | M32: 18 | O32: 1.01.01.007 | P32: Diferencia de Caja | Q32: 1736
A33: 1.01.01.01.28 | B33: Caja Buffo | C33: 3436 | D33: N | H33: NO | I33: =+IFERROR(VLOOKUP(C33,'Mov 2023 hasta ahora '!$C$2:$D$314,2,FALSE),"NO") -> 2 | J33: Eliminar | K33: 5 | L33: PATRIMONIAL | M33: 18 | O33: 1.01.01.007 | P33: Diferencia de Caja | Q33: 1736
A34: 1.01.01.01.29 | B34: Caja Seg Solano Vera - Bco Rio Efect | C34: 3440 | H34: NO | I34: =+IFERROR(VLOOKUP(C34,'Mov 2023 hasta ahora '!$C$2:$D$314,2,FALSE),"NO") -> NO | J34: Eliminar | K34: 5 | L34: PATRIMONIAL | M34: 18 | O34: 1.01.01.007 | P34: Diferencia de Caja | Q34: 1736
A35: 1.01.01.01.30 | B35: Caja Seg Efectivo Buffo - Bco Rio | C35: 3462 | H35: NO | I35: =+IFERROR(VLOOKUP(C35,'Mov 2023 hasta ahora '!$C$2:$D$314,2,FALSE),"NO") -> NO | J35: Eliminar | K35: 5 | L35: PATRIMONIAL | M35: 18 | O35: 1.01.01.007 | P35: Diferencia de Caja | Q35: 1736
A36: 1.01.01.01.31 | B36: Caja Compensacion | C36: 3600 | I36: =+IFERROR(VLOOKUP(C36,'Mov 2023 hasta ahora '!$C$2:$D$314,2,FALSE),"NO") -> 2160 | J36: ok | K36: 5 | L36: PATRIMONIAL | M36: 18 | O36: 1.01.01.009 | P36: Caja Compensación | Q36: 3600 | R36: N
A37: 1.01.01.01.32 | B37: Caja Fiduciario Fid.San Pablo Este | C37: 3844 | D37: N | I37: =+IFERROR(VLOOKUP(C37,'Mov 2023 hasta ahora '!$C$2:$D$314,2,FALSE),"NO") -> 74 | J37: ok | K37: 5 | L37: PATRIMONIAL | M37: 18 | O37: 1.01.01.010 | P37: Caja Fiduciario Fid.San Pablo Este | Q37: 3844 | R37: N
A38: 1.01.01.01.33 | B38: Caja Administración | C38: 3870 | I38: =+IFERROR(VLOOKUP(C38,'Mov 2023 hasta ahora '!$C$2:$D$314,2,FALSE),"NO") -> 2007 | J38: ok | K38: 5 | L38: PATRIMONIAL | M38: 18 | O38: 1.01.01.011 | P38: Caja Administración | Q38: 3870 | R38: N
A39: 1.01.01.01.34 | B39: Caja Seg U$S-Nro 4-Bco Francés-Torres SP SRL | C39: 3874 | D39: N | F39: 2 | I39: =+IFERROR(VLOOKUP(C39,'Mov 2023 hasta ahora '!$C$2:$D$314,2,FALSE),"NO") -> 23 | J39: ok | K39: 5 | L39: PATRIMONIAL | M39: 18 | O39: 1.01.01.012 | P39: Caja Seg U$S-Nro 4-Bco Francés-Torres SP SRL | Q39: 3874 | R39: N | T39: =+F39 -> 2
A40: 1.01.01.02 | B40: BANCOS | D40: N | I40: =+IFERROR(VLOOKUP(C40,'Mov 2023 hasta ahora '!$C$2:$D$314,2,FALSE),"NO") -> NO | J40: ok | K40: 4 | L40: PATRIMONIAL | M40: 14
A41: 1.01.01.02.01 | B41: Bancos Cta Cte | C41: 4 | D41: N | E41: 3 | I41: =+IFERROR(VLOOKUP(C41,'Mov 2023 hasta ahora '!$C$2:$D$314,2,FALSE),"NO") -> 11263 | J41: ok | K41: 5 | L41: PATRIMONIAL | M41: 18 | O41: 1.01.02.001 | P41: Bancos Cta Cte | Q41: 4 | R41: N | S41: =+E41 -> 3
A42: 1.01.01.02.02 | B42: Bancos Cajas de Ahorro | C42: 5 | D42: N | E42: 3 | I42: =+IFERROR(VLOOKUP(C42,'Mov 2023 hasta ahora '!$C$2:$D$314,2,FALSE),"NO") -> NO | J42: ok | K42: 5 | L42: PATRIMONIAL | M42: 18 | O42: 1.01.02.002 | P42: Bancos Cajas de Ahorro | Q42: 5 | R42: N | S42: =+E42 -> 3
A43: 1.01.01.02.03 | B43: Banco cta cte Dolares | C43: 3607 | D43: N | E43: 3 | F43: 2 | I43: =+IFERROR(VLOOKUP(C43,'Mov 2023 hasta ahora '!$C$2:$D$314,2,FALSE),"NO") -> NO | J43: ok | K43: 5 | L43: PATRIMONIAL | M43: 18 | O43: 1.01.02.003 | P43: Banco cta cte U$S | Q43: 3607 | R43: N | S43: =+E43 -> 3 | T43: =+F43 -> 2
A44: 1.01.02 | B44: INVERSIONES | D44: N | I44: =+IFERROR(VLOOKUP(C44,'Mov 2023 hasta ahora '!$C$2:$D$314,2,FALSE),"NO") -> NO | J44: ok | K44: 3 | L44: PATRIMONIAL | M44: 10
A45: 1.01.02.01 | B45: INVERSIONES EN TITULOS Y ACCIONES | D45: N | I45: =+IFERROR(VLOOKUP(C45,'Mov 2023 hasta ahora '!$C$2:$D$314,2,FALSE),"NO") -> NO | J45: ok | K45: 4 | L45: PATRIMONIAL | M45: 14
A46: 1.01.02.01.01 | B46: Valores Mobiliarios | C46: 6 | D46: N | I46: =+IFERROR(VLOOKUP(C46,'Mov 2023 hasta ahora '!$C$2:$D$314,2,FALSE),"NO") -> NO | J46: ok | K46: 5 | L46: PATRIMONIAL | M46: 18 | O46: 1.02.01.001 | P46: Valores Mobiliarios | Q46: 6 | R46: N
A47: 1.01.02.01.02 | B47: Titulos Publicos | C47: 7 | D47: N | I47: =+IFERROR(VLOOKUP(C47,'Mov 2023 hasta ahora '!$C$2:$D$314,2,FALSE),"NO") -> NO | J47: ok | K47: 5 | L47: PATRIMONIAL | M47: 18 | O47: 1.02.01.002 | P47: Títulos Públicos | Q47: 7 | R47: N
A48: 1.01.02.01.03 | B48: Fondo comÃ n de inversiÃ²n | C48: 1977 | D48: N | E48: 3 | I48: =+IFERROR(VLOOKUP(C48,'Mov 2023 hasta ahora '!$C$2:$D$314,2,FALSE),"NO") -> NO | J48: ok | K48: 5 | L48: PATRIMONIAL | M48: 18 | O48: 1.02.01.003 | P48: Fondo común de inversión | Q48: 1977 | R48: N | S48: =+E48 -> 3
A49: 1.01.02.02 | B49: INVERSIONES EN PLAZOS FIJOS | D49: N | I49: =+IFERROR(VLOOKUP(C49,'Mov 2023 hasta ahora '!$C$2:$D$314,2,FALSE),"NO") -> NO | J49: Eliminar | K49: 4 | L49: PATRIMONIAL | M49: 14
A50: 1.01.02.02.01 | B50: Plazos Fijos | C50: 8 | D50: N | E50: 3 | I50: =+IFERROR(VLOOKUP(C50,'Mov 2023 hasta ahora '!$C$2:$D$314,2,FALSE),"NO") -> NO | J50: ok | K50: 5 | L50: PATRIMONIAL | M50: 18 | O50: 1.02.01.004 | P50: Plazos Fijos | Q50: 8 | R50: N | S50: =+E50 -> 3
A51: 1.01.02.02.02 | B51: Intereses Plazo Fijo No Devengados | C51: 9 | D51: N | I51: =+IFERROR(VLOOKUP(C51,'Mov 2023 hasta ahora '!$C$2:$D$314,2,FALSE),"NO") -> NO | J51: ok | K51: 5 | L51: PATRIMONIAL | M51: 18 | O51: 1.02.01.005 | P51: Intereses Plazo Fijo No Devengados | Q51: 9 | R51: N
A52: 1.01.02.02.03 | B52: Plazo fijo en dolares | C52: 1973 | D52: N | E52: 3 | F52: 2 | I52: =+IFERROR(VLOOKUP(C52,'Mov 2023 hasta ahora '!$C$2:$D$314,2,FALSE),"NO") -> NO | J52: ok | K52: 5 | L52: PATRIMONIAL | M52: 18 | O52: 1.02.01.006 | P52: Plazo fijo en dólares | Q52: 1973 | R52: N | S52: =+E52 -> 3 | T52: =+F52 -> 2
A53: 1.01.02.03 | B53: INVERSIONES PERMANENTES | D53: N | I53: =+IFERROR(VLOOKUP(C53,'Mov 2023 hasta ahora '!$C$2:$D$314,2,FALSE),"NO") -> NO | J53: Enviair a inversiones permanentes y dividir entre inmuebles y participaciones societarias | K53: 4 | L53: PATRIMONIAL | M53: 14
A54: 1.01.02.03.01 | B54: Inversiones en inmuebles por Canjes | C54: 10 | D54: N | H54: NO | I54: =+IFERROR(VLOOKUP(C54,'Mov 2023 hasta ahora '!$C$2:$D$314,2,FALSE),"NO") -> 2 | J54: Eliminar | K54: 5 | L54: PATRIMONIAL | M54: 18 | O54: 1.05.02.006 | P54: Casas y Departamentos Recibidos | Q54: 93
A55: 1.01.02.03.02 | B55: (No Usar)Inversiones en otras empresas | C55: 1562 | H55: NO | I55: =+IFERROR(VLOOKUP(C55,'Mov 2023 hasta ahora '!$C$2:$D$314,2,FALSE),"NO") -> NO | J55: Eliminar | K55: 5 | L55: PATRIMONIAL | M55: 18 | O55: 1.02.02.001 | P55: Inversiones en otras empresas | Q55: 1905
A56: 1.01.02.03.03 | B56: Inversiones en Inmuebles | C56: 56 | D56: N | I56: =+IFERROR(VLOOKUP(C56,'Mov 2023 hasta ahora '!$C$2:$D$314,2,FALSE),"NO") -> 155 | J56: Enviair a inversiones permanentes y dividir entre inmuebles y participaciones societarias | K56: 5 | L56: PATRIMONIAL | M56: 18 | O56: 1.02.02.002 | P56: Inversiones en Inmuebles | Q56: 56 | R56: N
A57: 1.01.02.03.04 | B57: Am.Acum. Inm.p/ inversion | C57: 2097 | D57: N | I57: =+IFERROR(VLOOKUP(C57,'Mov 2023 hasta ahora '!$C$2:$D$314,2,FALSE),"NO") -> NO | J57: Enviair a inversiones permanentes y dividir entre inmuebles y participaciones societarias | K57: 5 | L57: PATRIMONIAL | M57: 18 | O57: 1.02.02.003 | P57: Am.Acum. Inm.p/ inversión | Q57: 2097 | R57: N
A58: 1.01.02.04 | B58: OTRAS INVERSIONES | I58: =+IFERROR(VLOOKUP(C58,'Mov 2023 hasta ahora '!$C$2:$D$314,2,FALSE),"NO") -> NO | J58: ok | K58: 4 | L58: PATRIMONIAL | M58: 14
A59: 1.01.02.04.01 | B59: Inversiones varias | C59: 3820 | D59: N | I59: =+IFERROR(VLOOKUP(C59,'Mov 2023 hasta ahora '!$C$2:$D$314,2,FALSE),"NO") -> NO | J59: ok | K59: 5 | L59: PATRIMONIAL | M59: 18 | O59: 1.02.03.001 | P59: Inversiones varias | Q59: 3820 | R59: N
A60: 1.01.03 | B60: CREDITOS POR VENTAS | D60: N | I60: =+IFERROR(VLOOKUP(C60,'Mov 2023 hasta ahora '!$C$2:$D$314,2,FALSE),"NO") -> NO | J60: ok | K60: 3 | L60: PATRIMONIAL | M60: 10
A61: 1.01.03.01 | B61: CREDITOS A VENCER | D61: N | I61: =+IFERROR(VLOOKUP(C61,'Mov 2023 hasta ahora '!$C$2:$D$314,2,FALSE),"NO") -> NO | J61: Crear Creditos por alquileres, creditos por op de loteos, Creditos otros creditos | K61: 4 | L61: PATRIMONIAL | M61: 14
A62: 1.01.03.01.01 | B62: Deudores por Ventas Agropecuarias | C62: 11 | D62: N | E62: 1 | H62: NO | I62: =+IFERROR(VLOOKUP(C62,'Mov 2023 hasta ahora '!$C$2:$D$314,2,FALSE),"NO") -> NO | J62: Eliminar | K62: 5 | L62: PATRIMONIAL | M62: 18 | O62: 1.03.01.003 | P62: Documentos a Cobrar | Q62: 14
A63: 1.01.03.01.02 | B63: Fiduciantes | C63: 12 | D63: N | E63: 1 | H63: -7747154.4 | I63: =+IFERROR(VLOOKUP(C63,'Mov 2023 hasta ahora '!$C$2:$D$314,2,FALSE),"NO") -> NO | J63: Eliminar | K63: 5 | L63: PATRIMONIAL | M63: 18 | O63: 1.03.01.001 | P63: Fiduciantes | Q63: 12 | R63: N | S63: =+E63 -> 1
A64: 1.01.03.01.03 | B64: Contratos de Locacion a Cobrar | C64: 13 | D64: N | E64: 1 | I64: =+IFERROR(VLOOKUP(C64,'Mov 2023 hasta ahora '!$C$2:$D$314,2,FALSE),"NO") -> 3748 | J64: ok | K64: 5 | L64: PATRIMONIAL | M64: 18 | O64: 1.03.01.002 | P64: Contratos de Locación a Cobrar | Q64: 13 | R64: N | S64: =+E64 -> 1
A65: 1.01.03.01.04 | B65: Documentos a Cobrar | C65: 14 | D65: N | E65: 1 | I65: =+IFERROR(VLOOKUP(C65,'Mov 2023 hasta ahora '!$C$2:$D$314,2,FALSE),"NO") -> NO | J65: ok | K65: 5 | L65: PATRIMONIAL | M65: 18 | O65: 1.03.01.003 | P65: Documentos a Cobrar | Q65: 14 | R65: N | S65: =+E65 -> 1
A66: 1.01.03.01.05 | B66: Cheques de Terceros a Cobrar | C66: 15 | D66: N | E66: 1 | I66: =+IFERROR(VLOOKUP(C66,'Mov 2023 hasta ahora '!$C$2:$D$314,2,FALSE),"NO") -> 1555 | J66: ok | K66: 5 | L66: PATRIMONIAL | M66: 18 | O66: 1.03.01.004 | P66: Cheques de Terceros a Cobrar | Q66: 15 | R66: N | S66: =+E66 -> 1
A67: 1.01.03.01.06 | B67: Alquileres a Cobrar | C67: 141 | D67: N | E67: 1 | I67: =+IFERROR(VLOOKUP(C67,'Mov 2023 hasta ahora '!$C$2:$D$314,2,FALSE),"NO") -> 3969 | J67: ok | K67: 5 | L67: PATRIMONIAL | M67: 18 | O67: 1.03.01.005 | P67: Alquileres a Cobrar | Q67: 141 | R67: N | S67: =+E67 -> 1
A68: 1.01.03.01.07 | B68: Expensas a Cobrar | C68: 142 | D68: N | E68: 1 | I68: =+IFERROR(VLOOKUP(C68,'Mov 2023 hasta ahora '!$C$2:$D$314,2,FALSE),"NO") -> NO | J68: ok | K68: 5 | L68: PATRIMONIAL | M68: 18 | O68: 1.03.01.006 | P68: Expensas a Cobrar | Q68: 142 | R68: N | S68: =+E68 -> 1
A69: 1.01.03.01.08 | B69: Depositos en Garantia a Cobrar | C69: 143 | D69: N | E69: 1 | I69: =+IFERROR(VLOOKUP(C69,'Mov 2023 hasta ahora '!$C$2:$D$314,2,FALSE),"NO") -> 141 | J69: ok | K69: 5 | L69: PATRIMONIAL | M69: 18 | O69: 1.03.01.007 | P69: Depósitos en Garantía a Cobrar | Q69: 143 | R69: N | S69: =+E69 -> 1
A70: 1.01.03.01.09 | B70: Deudores por Ventas de inmuebles | C70: 347 | D70: N | E70: 1 | I70: =+IFERROR(VLOOKUP(C70,'Mov 2023 hasta ahora '!$C$2:$D$314,2,FALSE),"NO") -> 28 | J70: ok | K70: 5 | L70: PATRIMONIAL | M70: 18 | O70: 1.03.01.008 | P70: Deudores por Ventas de inmuebles | Q70: 347 | R70: N | S70: =+E70 -> 1
A71: 1.01.03.01.10 | B71: OperaciÃ³n LocaciÃ³n Inm. 3 | C71: 1392 | D71: N | E71: 1 | I71: =+IFERROR(VLOOKUP(C71,'Mov 2023 hasta ahora '!$C$2:$D$314,2,FALSE),"NO") -> 23472 | J71: ok | K71: 5 | L71: PATRIMONIAL | M71: 18 | O71: 1.03.01.009 | P71: Operación Locación Inm. 3 | Q71: 1392 | R71: N | S71: =+E71 -> 1
A72: 1.01.03.01.11 | B72: Comisiones a Cobrar | C72: 1347 | D72: N | E72: 1 | I72: =+IFERROR(VLOOKUP(C72,'Mov 2023 hasta ahora '!$C$2:$D$314,2,FALSE),"NO") -> 2215 | J72: ok | K72: 5 | L72: PATRIMONIAL | M72: 18 | O72: 1.03.01.010 | P72: Comisiones a Cobrar | Q72: 1347 | R72: N | S72: =+E72 -> 1
A73: 1.01.03.01.12 | B73: Cheques de 3 en Custodia | C73: 341 | D73: N | E73: 1 | I73: =+IFERROR(VLOOKUP(C73,'Mov 2023 hasta ahora '!$C$2:$D$314,2,FALSE),"NO") -> NO | J73: ok | K73: 5 | L73: PATRIMONIAL | M73: 18 | O73: 1.03.01.011 | P73: Cheques de 3 en Custodia | Q73: 341 | R73: N | S73: =+E73 -> 1
A74: 1.01.03.01.13 | B74: Intereses a Cobrar | C74: 1389 | D74: N | E74: 1 | I74: =+IFERROR(VLOOKUP(C74,'Mov 2023 hasta ahora '!$C$2:$D$314,2,FALSE),"NO") -> NO | J74: ok | K74: 5 | L74: PATRIMONIAL | M74: 18 | O74: 1.03.01.012 | P74: Intereses a Cobrar | Q74: 1389 | R74: N | S74: =+E74 -> 1
A75: 1.01.03.01.14 | B75: Alquileres de 3 a Cobrar | C75: 1390 | D75: N | E75: 1 | I75: =+IFERROR(VLOOKUP(C75,'Mov 2023 hasta ahora '!$C$2:$D$314,2,FALSE),"NO") -> 21145 | J75: ok | K75: 5 | L75: PATRIMONIAL | M75: 18 | O75: 1.03.01.013 | P75: Alquileres de 3 a Cobrar | Q75: 1390 | R75: N | S75: =+E75 -> 1
... A78: 1.01.03.01.17 | B78: Alquileres No Devengados | C78: 144 | D78: N | E78: 1 | I78: =+IFERROR(VLOOKUP(C78,'Mov 2023 hasta ahora '!$C$2:$D$314,2,FALSE),"NO") -> 1971 | J78: ok | K78: 5 | L78: PATRIMONIAL | M78: 18 | O78: 1.03.01.016 | P78: Alquileres No Devengados | Q78: 144 | R78: N | S78: =+E78 -> 1
A79: 1.01.03.01.18 | B79: Cuentas a cobrar en moneda extranjera | C79: 1972 | D79: N | E79: 1 | F79: 2 | I79: =+IFERROR(VLOOKUP(C79,'Mov 2023 hasta ahora '!$C$2:$D$314,2,FALSE),"NO") -> NO | J79: ok | K79: 5 | L79: PATRIMONIAL | M79: 18 | O79: 1.03.01.017 | P79: Cuentas a cobrar en moneda extranjera | Q79: 1972 | R79: N | S79: =+E79 -> 1 | T79: =+F79 -> 2
A80: 1.01.03.01.19 | B80: Certificado provisorio a cobrar | C80: 2447 | D80: N | E80: 1 | H80: NO | I80: =+IFERROR(VLOOKUP(C80,'Mov 2023 hasta ahora '!$C$2:$D$314,2,FALSE),"NO") -> NO | J80: Eliminar | K80: 5 | L80: PATRIMONIAL | M80: 18 | O80: 1.03.01.003 | P80: Documentos a Cobrar | Q80: 14
A81: 1.01.03.01.20 | B81: Deudores por Ventas LOTEOS GCI | C81: 155 | D81: N | E81: 1 | H81: NO | I81: =+IFERROR(VLOOKUP(C81,'Mov 2023 hasta ahora '!$C$2:$D$314,2,FALSE),"NO") -> 4 | J81: ok | K81: 5 | L81: PATRIMONIAL | M81: 18 | O81: 1.03.01.018 | P81: Deudores por Ventas LOTEOS GCI | Q81: 3866 | R81: N | S81: =+E81 -> 1
A82: 1.01.03.01.21 | B82: Deudores por Ventas LOTEOS ECI | C82: 1730 | D82: N | E82: 1 | H82: NO | I82: =+IFERROR(VLOOKUP(C82,'Mov 2023 hasta ahora '!$C$2:$D$314,2,FALSE),"NO") -> NO | J82: Eliminar | K82: 5 | L82: PATRIMONIAL | M82: 18 | O82: 1.03.01.021 | P82: Deudores por Ventas LOTEOS OTROS | Q82: 1822
A83: 1.01.03.01.22 | B83: Deudores por Ventas LOTEOS AW | C83: 1728 | D83: N | E83: 1 | H83: 34754.17 | I83: =+IFERROR(VLOOKUP(C83,'Mov 2023 hasta ahora '!$C$2:$D$314,2,FALSE),"NO") -> NO | J83: ok | K83: 5 | L83: PATRIMONIAL | M83: 18 | O83: 1.03.01.019 | P83: Deudores por Ventas LOTEOS AW | Q83: 3867 | R83: N | S83: =+E83 -> 1
A84: 1.01.03.01.23 | B84: Deudores por Ventas LOTEOS EL | C84: 1729 | D84: N | E84: 1 | H84: -1000 | I84: =+IFERROR(VLOOKUP(C84,'Mov 2023 hasta ahora '!$C$2:$D$314,2,FALSE),"NO") -> NO | J84: ok | K84: 5 | L84: PATRIMONIAL | M84: 18 | O84: 1.03.01.020 | P84: Deudores por Ventas LOTEOS EL | Q84: 3868 | R84: N | S84: =+E84 -> 1
A85: 1.01.03.01.24 | B85: Deudores por Ventas LOTEOS COUNTRY | C85: 1822 | E85: 1 | H85: NO | I85: =+IFERROR(VLOOKUP(C85,'Mov 2023 hasta ahora '!$C$2:$D$314,2,FALSE),"NO") -> NO | J85: ok | K85: 5 | L85: PATRIMONIAL | M85: 18 | O85: 1.03.01.021 | P85: Deudores por Ventas LOTEOS OTROS | Q85: 1822 | R85: N | S85: =+E85 -> 1
A86: 1.01.03.01.25 | B86: Operacion Venta inm.3 | C86: 2584 | D86: N | E86: 1 | H86: NO | I86: =+IFERROR(VLOOKUP(C86,'Mov 2023 hasta ahora '!$C$2:$D$314,2,FALSE),"NO") -> NO | J86: Eliminar | K86: 5 | L86: PATRIMONIAL | M86: 18 | O86: 1.03.01.021 | P86: Deudores por Ventas LOTEOS OTROS | Q86: 1822
A87: 1.01.03.01.26 | B87: Caja seg.Maipu Valores en Custodia PCIW 3/4 | C87: 2697 | D87: N | E87: 1 | H87: NO | I87: =+IFERROR(VLOOKUP(C87,'Mov 2023 hasta ahora '!$C$2:$D$314,2,FALSE),"NO") -> NO | J87: Eliminar | K87: 5 | L87: PATRIMONIAL | M87: 18 | O87: 1.03.01.003 | P87: Documentos a Cobrar | Q87: 14
A88: 1.01.03.01.27 | B88: Ds.vta de Lotes x cta y orden de 3ros | C88: 3429 | D88: N | E88: 1 | H88: NO | I88: =+IFERROR(VLOOKUP(C88,'Mov 2023 hasta ahora '!$C$2:$D$314,2,FALSE),"NO") -> NO | J88: Eliminar | K88: 5 | L88: PATRIMONIAL | M88: 18 | O88: 1.03.01.021 | P88: Deudores por Ventas LOTEOS OTROS | Q88: 1822
A89: 1.01.03.01.28 | B89: Ds.vta de Lotes x op. San Lorenzo Socios | C89: 3457 | D89: N | E89: 1 | H89: NO | I89: =+IFERROR(VLOOKUP(C89,'Mov 2023 hasta ahora '!$C$2:$D$314,2,FALSE),"NO") -> NO | J89: Eliminar | K89: 5 | L89: PATRIMONIAL | M89: 18 | O89: 1.03.01.021 | P89: Deudores por Ventas LOTEOS OTROS | Q89: 1822
A90: 1.01.03.01.29 | B90: Ds. Vta de Lotes Prados de Yerba Buena | C90: 3833 | D90: N | E90: 1 | H90: NO | I90: =+IFERROR(VLOOKUP(C90,'Mov 2023 hasta ahora '!$C$2:$D$314,2,FALSE),"NO") -> 1368 | J90: Eliminar | K90: 5 | L90: PATRIMONIAL | M90: 18 | O90: 1.03.01.021 | P90: Deudores por Ventas LOTEOS OTROS | Q90: 1822
A91: 1.01.03.01.30 | B91: Otros Creditos a Cobrar | C91: 3851 | D91: N | I91: =+IFERROR(VLOOKUP(C91,'Mov 2023 hasta ahora '!$C$2:$D$314,2,FALSE),"NO") -> 6 | K91: 5 | L91: PATRIMONIAL | M91: 18 | O91: 1.03.01.022 | P91: Otros Créditos a Cobrar | Q91: 3851 | R91: N
A92: 1.01.03.01.40 | B92: Diferencia Cheques de 3 a Cobrar | C92: 1737 | D92: N | E92: 1 | H92: NO | I92: =+IFERROR(VLOOKUP(C92,'Mov 2023 hasta ahora '!$C$2:$D$314,2,FALSE),"NO") -> NO | J92: Eliminar | K92: 5 | L92: PATRIMONIAL | M92: 18 | O92: 1.03.01.003 | P92: Documentos a Cobrar | Q92: 14
A93: 1.01.03.01.41 | B93: Interes por financ. no devengado | C93: 2764 | D93: N | I93: =+IFERROR(VLOOKUP(C93,'Mov 2023 hasta ahora '!$C$2:$D$314,2,FALSE),"NO") -> 38 | J93: Enviar a Otros Creditos | K93: 5 | L93: PATRIMONIAL | M93: 18 | O93: 1.03.01.023 | P93: Interes por financ. no devengado | Q93: 2764 | R93: N
A94: 1.01.03.01.42 | B94: Alq.de 3 a cobrar en gestiÃ³n judicial | C94: 2866 | D94: N | E94: 1 | H94: 38720.31 | I94: =+IFERROR(VLOOKUP(C94,'Mov 2023 hasta ahora '!$C$2:$D$314,2,FALSE),"NO") -> NO | J94: Enivar a Ds en gestion | K94: 5 | L94: PATRIMONIAL | M94: 18 | O94: 1.03.01.024 | P94: Deudores en Gestión | Q94: 16
A95: 1.01.03.01.43 | B95: Loteo Prados del Libertador GCI | C95: 3449 | D95: N | E95: 1 | H95: 139500 | I95: =+IFERROR(VLOOKUP(C95,'Mov 2023 hasta ahora '!$C$2:$D$314,2,FALSE),"NO") -> NO | J95: Eliminar | K95: 5 | L95: PATRIMONIAL | M95: 18 | O95: 1.03.01.018 | P95: Deudores por Ventas LOTEOS GCI | Q95: 3866
A96: 1.01.03.01.44 | B96: Loteo Prados del Libertador AW | C96: 3450 | D96: N | E96: 1 | H96: NO | I96: =+IFERROR(VLOOKUP(C96,'Mov 2023 hasta ahora '!$C$2:$D$314,2,FALSE),"NO") -> NO | J96: Eliminar | K96: 5 | L96: PATRIMONIAL | M96: 18 | O96: 1.03.01.019 | P96: Deudores por Ventas LOTEOS AW | Q96: 3867
A97: 1.01.03.01.45 | B97: Cheques Buffo - Cartera | C97: 3459 | D97: N | E97: 1 | H97: NO | I97: =+IFERROR(VLOOKUP(C97,'Mov 2023 hasta ahora '!$C$2:$D$314,2,FALSE),"NO") -> NO | J97: Eliminar | K97: 5 | L97: PATRIMONIAL | M97: 18 | O97: 1.03.01.003 | P97: Documentos a Cobrar | Q97: 14
A98: 1.01.03.01.46 | B98: Cheques Buffo - Caja Seg. | C98: 3460 | D98: N | E98: 1 | H98: NO | I98: =+IFERROR(VLOOKUP(C98,'Mov 2023 hasta ahora '!$C$2:$D$314,2,FALSE),"NO") -> NO | J98: Eliminar | K98: 5 | L98: PATRIMONIAL | M98: 18 | O98: 1.03.01.003 | P98: Documentos a Cobrar | Q98: 14
A99: 1.01.03.01.48 | B99: Loteo Prados del Libertador EL 1 Etapa | C99: 3473 | D99: N | E99: 1 | H99: NO | I99: =+IFERROR(VLOOKUP(C99,'Mov 2023 hasta ahora '!$C$2:$D$314,2,FALSE),"NO") -> NO | J99: Eliminar | K99: 5 | L99: PATRIMONIAL | M99: 18 | O99: 1.03.01.020 | P99: Deudores por Ventas LOTEOS EL | Q99: 3868
A100: 1.01.03.01.49 | B100: Prados del Libertador AW 2 Etapa | C100: 3483 | E100: 1 | H100: NO | I100: =+IFERROR(VLOOKUP(C100,'Mov 2023 hasta ahora '!$C$2:$D$314,2,FALSE),"NO") -> NO | J100: Eliminar | K100: 5 | L100: PATRIMONIAL | M100: 18 | O100: 1.03.01.019 | P100: Deudores por Ventas LOTEOS AW | Q100: 3867
A101: 1.01.03.01.50 | B101: Prados del Libertador GCI 2 Etapa | C101: 3488 | E101: 1 | H101: NO | I101: =+IFERROR(VLOOKUP(C101,'Mov 2023 hasta ahora '!$C$2:$D$314,2,FALSE),"NO") -> NO | J101: Eliminar | K101: 5 | L101: PATRIMONIAL | M101: 18 | O101: 1.03.01.018 | P101: Deudores por Ventas LOTEOS GCI | Q101: 3866
A102: 1.01.03.01.51 | B102: Loteo Prados del Libertador Marcos W. | C102: 3491 | E102: 1 | H102: NO | I102: =+IFERROR(VLOOKUP(C102,'Mov 2023 hasta ahora '!$C$2:$D$314,2,FALSE),"NO") -> 6 | J102: Eliminar | K102: 5 | L102: PATRIMONIAL | M102: 18 | O102: 1.03.01.021 | P102: Deudores por Ventas LOTEOS OTROS | Q102: 1822
...

Sheet Mov 2023 hasta ahora 
A1: CODCTA | B1: DESCRIP | C1: NROCTA | D1: COUNT(*)
A2: 201020103 | B2: ART a pagar | C2: 45 | D2: 52
A3: 201020105 | B3: UOCRA a pagar | C3: 47 | D3: 54
A4: 301010101 | B4: Capital Social | C4: 134 | D4: 2
A5: 301010103 | B5: Aportes Irrevocables | C5: 136 | D5: 226
A6: 4331035660102 | B6: Alq x cta de 3 -Maipu 605-Alquileres | C6: 2283 | D6: 1386
A7: 101040122 | B7: Ingr. Brutos Saldo a Favor | C7: 1888 | D7: 266
A8: 5010107230001 | B8: Revestimiento-Revestimiento-Materiales | C8: 537 | D8: 2
A9: 5044115600067 | B9: Gs a Distribuir-Vs M Obra-Impresos y Util | C9: 1825 | D9: 7
A10: 101040230 | B10: Serv.contratados a cobrar | C10: 1980 | D10: 138
A11: 5918182860070 | B11: Gs administra-Gs Escrituras | C11: 1254 | D11: 5
A12: 5918182890117 | B12: Imp y Tasas-TACIS - TEM | C12: 1270 | D12: 54
A13: 5918182890126 | B13: Imp y Tasas-Otros Imp y Tas | C13: 1275 | D13: 360
... A314: 4217730010005 | B314: Gcia Batia Loteo Prados del Libertador Sofia L II | C314: 3849 | D314: 8
